sohampdf/__init__.py
sohampdf/pdf2text.py
SohamPDF-1.1.dist-info/LICENSE
SohamPDF-1.1.dist-info/METADATA
SohamPDF-1.1.dist-info/WHEEL
SohamPDF-1.1.dist-info/top_level.txt
SohamPDF-1.1.dist-info/RECORD
